pyepc/__init__.py
pyepc/epc.py
pyepc/exceptions.py
pyepc/sgtin.py
pyepc/sscc.py
pyepc/utils.py
pyepc-0.5.0.dist-info/LICENSE
pyepc-0.5.0.dist-info/METADATA
pyepc-0.5.0.dist-info/WHEEL
pyepc-0.5.0.dist-info/top_level.txt
pyepc-0.5.0.dist-info/RECORD
