Metadata-Version: 2.1
Name: pyepc
Version: 0.5.0
Summary: Python utility to encode/decode GS1 EPCs
Home-page: https://github.com/fulfilio/pyepc
Author: Fulfil.IO Inc.
Author-email: help@fulfil.io
License: MIT license
Keywords: pyepc epc
Classifier: Development Status :: 5 - Production/Stable
Classifier: Intended Audience :: Developers
Classifier: License :: OSI Approved :: MIT License
Classifier: Natural Language :: English
Classifier: Programming Language :: Python :: 3
Classifier: Programming Language :: Python :: 3.9
Classifier: Programming Language :: Python :: 3.10
Classifier: Programming Language :: Python :: 3.11
Requires-Python: >=3.9
License-File: LICENSE
